Metadata-Version: 1.0
Name: basedatosRho
Version: 1.0.2
Summary: paquete de base de datos
Home-page: UNKNOWN
Author: Roberto O.v
Author-email: ovr.roberto@gmail.com
License: UNKNOWN
Platform: UNKNOWN
